[
  {
    "Metric": "commit-latency-avg",
    "Description": "The average execution time in ms, for committing, across all running tasks of this thread.",
    "MBean": "kafka.streams:type=stream-thread-metrics,thread-id=([-.\\w]+)"
  },
  {
    "Metric": "commit-latency-max",
    "Description": "The maximum execution time in ms, for committing, across all running tasks of this thread.",
    "MBean": "kafka.streams:type=stream-thread-metrics,thread-id=([-.\\w]+)"
  },
  {
    "Metric": "poll-latency-avg",
    "Description": "The average execution time in ms, for consumer polling.",
    "MBean": "kafka.streams:type=stream-thread-metrics,thread-id=([-.\\w]+)"
  },
  {
    "Metric": "poll-latency-max",
    "Description": "The maximum execution time in ms, for consumer polling.",
    "MBean": "kafka.streams:type=stream-thread-metrics,thread-id=([-.\\w]+)"
  },
  {
    "Metric": "process-latency-avg",
    "Description": "The average execution time in ms, for processing.",
    "MBean": "kafka.streams:type=stream-thread-metrics,thread-id=([-.\\w]+)"
  },
  {
    "Metric": "process-latency-max",
    "Description": "The maximum execution time in ms, for processing.",
    "MBean": "kafka.streams:type=stream-thread-metrics,thread-id=([-.\\w]+)"
  },
  {
    "Metric": "punctuate-latency-avg",
    "Description": "The average execution time in ms, for punctuating.",
    "MBean": "kafka.streams:type=stream-thread-metrics,thread-id=([-.\\w]+)"
  },
  {
    "Metric": "punctuate-latency-max",
    "Description": "The maximum execution time in ms, for punctuating.",
    "MBean": "kafka.streams:type=stream-thread-metrics,thread-id=([-.\\w]+)"
  },
  {
    "Metric": "commit-rate",
    "Description": "The average number of commits per second.",
    "MBean": "kafka.streams:type=stream-thread-metrics,thread-id=([-.\\w]+)"
  },
  {
    "Metric": "commit-total",
    "Description": "The total number of commit calls.",
    "MBean": "kafka.streams:type=stream-thread-metrics,thread-id=([-.\\w]+)"
  },
  {
    "Metric": "poll-rate",
    "Description": "The average number of consumer poll calls per second.",
    "MBean": "kafka.streams:type=stream-thread-metrics,thread-id=([-.\\w]+)"
  },
  {
    "Metric": "poll-total",
    "Description": "The total number of consumer poll calls.",
    "MBean": "kafka.streams:type=stream-thread-metrics,thread-id=([-.\\w]+)"
  },
  {
    "Metric": "process-rate",
    "Description": "The average number of processed records per second.",
    "MBean": "kafka.streams:type=stream-thread-metrics,thread-id=([-.\\w]+)"
  },
  {
    "Metric": "process-total",
    "Description": "The total number of processed records.",
    "MBean": "kafka.streams:type=stream-thread-metrics,thread-id=([-.\\w]+)"
  },
  {
    "Metric": "punctuate-rate",
    "Description": "The average number of punctuate calls per second.",
    "MBean": "kafka.streams:type=stream-thread-metrics,thread-id=([-.\\w]+)"
  },
  {
    "Metric": "punctuate-total",
    "Description": "The total number of punctuate calls.",
    "MBean": "kafka.streams:type=stream-thread-metrics,thread-id=([-.\\w]+)"
  },
  {
    "Metric": "task-created-rate",
    "Description": "The average number of tasks created per second.",
    "MBean": "kafka.streams:type=stream-thread-metrics,thread-id=([-.\\w]+)"
  },
  {
    "Metric": "task-created-total",
    "Description": "The total number of tasks created.",
    "MBean": "kafka.streams:type=stream-thread-metrics,thread-id=([-.\\w]+)"
  },
  {
    "Metric": "task-closed-rate",
    "Description": "The average number of tasks closed per second.",
    "MBean": "kafka.streams:type=stream-thread-metrics,thread-id=([-.\\w]+)"
  },
  {
    "Metric": "task-closed-total",
    "Description": "The total number of tasks closed.",
    "MBean": "kafka.streams:type=stream-thread-metrics,thread-id=([-.\\w]+)"
  },
  {
    "Metric": "blocked-time-ns-total",
    "Description": "The total time the thread spent blocked on kafka.",
    "MBean": "kafka.streams:type=stream-thread-metrics,thread-id=([-.\\w]+)"
  },
  {
    "Metric": "thread-start-time",
    "Description": "The time that the thread was started.",
    "MBean": "kafka.streams:type=stream-thread-metrics,thread-id=([-.\\w]+)"
  }
]